huaweicloudsdkeihealth/__init__.py
huaweicloudsdkeihealth/v1/__init__.py
huaweicloudsdkeihealth/v1/eihealth_async_client.py
huaweicloudsdkeihealth/v1/eihealth_client.py
huaweicloudsdkeihealth/v1/model/__init__.py
huaweicloudsdkeihealth/v1/model/action_type.py
huaweicloudsdkeihealth/v1/model/add_drug_database_file_req.py
huaweicloudsdkeihealth/v1/model/add_drug_database_file_request.py
huaweicloudsdkeihealth/v1/model/add_drug_database_file_response.py
huaweicloudsdkeihealth/v1/model/admet_request.py
huaweicloudsdkeihealth/v1/model/agency_dto.py
huaweicloudsdkeihealth/v1/model/agent_role.py
huaweicloudsdkeihealth/v1/model/agent_type.py
huaweicloudsdkeihealth/v1/model/app_dto.py
huaweicloudsdkeihealth/v1/model/app_filter_dto.py
huaweicloudsdkeihealth/v1/model/app_info_dto.py
huaweicloudsdkeihealth/v1/model/app_input_parameter_dto.py
huaweicloudsdkeihealth/v1/model/app_list_dto.py
huaweicloudsdkeihealth/v1/model/app_output_parameter_dto.py
huaweicloudsdkeihealth/v1/model/app_req.py
huaweicloudsdkeihealth/v1/model/app_src_req.py
huaweicloudsdkeihealth/v1/model/asset_resource_rsp.py
huaweicloudsdkeihealth/v1/model/asset_resource_status_enum.py
huaweicloudsdkeihealth/v1/model/base_model.py
huaweicloudsdkeihealth/v1/model/base_model_dto.py
huaweicloudsdkeihealth/v1/model/basic_drug_model.py
huaweicloudsdkeihealth/v1/model/batch_cancel_job_request.py
huaweicloudsdkeihealth/v1/model/batch_cancel_job_response.py
huaweicloudsdkeihealth/v1/model/batch_delete_data_req.py
huaweicloudsdkeihealth/v1/model/batch_delete_data_request.py
huaweicloudsdkeihealth/v1/model/batch_delete_data_response.py
huaweicloudsdkeihealth/v1/model/batch_delete_job_request.py
huaweicloudsdkeihealth/v1/model/batch_delete_job_response.py
huaweicloudsdkeihealth/v1/model/batch_delete_label_req.py
huaweicloudsdkeihealth/v1/model/batch_delete_label_request.py
huaweicloudsdkeihealth/v1/model/batch_delete_label_response.py
huaweicloudsdkeihealth/v1/model/batch_import_app_req.py
huaweicloudsdkeihealth-3.1.174.dist-info/METADATA
huaweicloudsdkeihealth-3.1.174.dist-info/WHEEL
huaweicloudsdkeihealth-3.1.174.dist-info/licenses/LICENSE
huaweicloudsdkeihealth-3.1.174.dist-info/RECORD
